{"nodes": [{"id": "c_users_jaisi_documents_react_projects_gts_katha_components_layout_navbar_tsx", "label": "Navbar.tsx", "file_type": "code", "source_file": "C:\\Users\\jaisi\\Documents\\React Projects\\gts-katha\\components\\layout\\Navbar.tsx", "source_location": "L1"}, {"id": "layout_navbar_navicon", "label": "NavIcon()", "file_type": "code", "source_file": "C:\\Users\\jaisi\\Documents\\React Projects\\gts-katha\\components\\layout\\Navbar.tsx", "source_location": "L22"}, {"id": "layout_navbar_isactive", "label": "isActive()", "file_type": "code", "source_file": "C:\\Users\\jaisi\\Documents\\React Projects\\gts-katha\\components\\layout\\Navbar.tsx", "source_location": "L50"}, {"id": "layout_navbar_handlelogout", "label": "handleLogout()", "file_type": "code", "source_file": "C:\\Users\\jaisi\\Documents\\React Projects\\gts-katha\\components\\layout\\Navbar.tsx", "source_location": "L55"}], "edges": [{"source": "c_users_jaisi_documents_react_projects_gts_katha_components_layout_navbar_tsx", "target": "link", "relation": "imports_from", "confidence": "EXTRACTED", "source_file": "C:\\Users\\jaisi\\Documents\\React Projects\\gts-katha\\components\\layout\\Navbar.tsx", "source_location": "L3", "weight": 1.0}, {"source": "c_users_jaisi_documents_react_projects_gts_katha_components_layout_navbar_tsx", "target": "next_auth", "relation": "imports_from", "confidence": "EXTRACTED", "source_file": "C:\\Users\\jaisi\\Documents\\React Projects\\gts-katha\\components\\layout\\Navbar.tsx", "source_location": "L4", "weight": 1.0}, {"source": "c_users_jaisi_documents_react_projects_gts_katha_components_layout_navbar_tsx", "target": "react", "relation": "imports_from", "confidence": "EXTRACTED", "source_file": "C:\\Users\\jaisi\\Documents\\React Projects\\gts-katha\\components\\layout\\Navbar.tsx", "source_location": "L5", "weight": 1.0}, {"source": "c_users_jaisi_documents_react_projects_gts_katha_components_layout_navbar_tsx", "target": "navigation", "relation": "imports_from", "confidence": "EXTRACTED", "source_file": "C:\\Users\\jaisi\\Documents\\React Projects\\gts-katha\\components\\layout\\Navbar.tsx", "source_location": "L6", "weight": 1.0}, {"source": "c_users_jaisi_documents_react_projects_gts_katha_components_layout_navbar_tsx", "target": "react", "relation": "imports_from", "confidence": "EXTRACTED", "source_file": "C:\\Users\\jaisi\\Documents\\React Projects\\gts-katha\\components\\layout\\Navbar.tsx", "source_location": "L7", "weight": 1.0}, {"source": "c_users_jaisi_documents_react_projects_gts_katha_components_layout_navbar_tsx", "target": "sonner", "relation": "imports_from", "confidence": "EXTRACTED", "source_file": "C:\\Users\\jaisi\\Documents\\React Projects\\gts-katha\\components\\layout\\Navbar.tsx", "source_location": "L8", "weight": 1.0}, {"source": "c_users_jaisi_documents_react_projects_gts_katha_components_layout_navbar_tsx", "target": "c_users_jaisi_documents_react_projects_gts_katha_components_layout_mobilemenudrawer", "relation": "imports_from", "confidence": "EXTRACTED", "source_file": "C:\\Users\\jaisi\\Documents\\React Projects\\gts-katha\\components\\layout\\Navbar.tsx", "source_location": "L9", "weight": 1.0}, {"source": "c_users_jaisi_documents_react_projects_gts_katha_components_layout_navbar_tsx", "target": "c_users_jaisi_documents_react_projects_gts_katha_components_layout_navbarsearch", "relation": "imports_from", "confidence": "EXTRACTED", "source_file": "C:\\Users\\jaisi\\Documents\\React Projects\\gts-katha\\components\\layout\\Navbar.tsx", "source_location": "L10", "weight": 1.0}, {"source": "c_users_jaisi_documents_react_projects_gts_katha_components_layout_navbar_tsx", "target": "c_users_jaisi_documents_react_projects_gts_katha_components_layout_usermenu", "relation": "imports_from", "confidence": "EXTRACTED", "source_file": "C:\\Users\\jaisi\\Documents\\React Projects\\gts-katha\\components\\layout\\Navbar.tsx", "source_location": "L11", "weight": 1.0}, {"source": "c_users_jaisi_documents_react_projects_gts_katha_components_layout_navbar_tsx", "target": "layout_navbar_navicon", "relation": "contains", "confidence": "EXTRACTED", "source_file": "C:\\Users\\jaisi\\Documents\\React Projects\\gts-katha\\components\\layout\\Navbar.tsx", "source_location": "L22", "weight": 1.0}, {"source": "c_users_jaisi_documents_react_projects_gts_katha_components_layout_navbar_tsx", "target": "layout_navbar_isactive", "relation": "contains", "confidence": "EXTRACTED", "source_file": "C:\\Users\\jaisi\\Documents\\React Projects\\gts-katha\\components\\layout\\Navbar.tsx", "source_location": "L50", "weight": 1.0}, {"source": "c_users_jaisi_documents_react_projects_gts_katha_components_layout_navbar_tsx", "target": "layout_navbar_handlelogout", "relation": "contains", "confidence": "EXTRACTED", "source_file": "C:\\Users\\jaisi\\Documents\\React Projects\\gts-katha\\components\\layout\\Navbar.tsx", "source_location": "L55", "weight": 1.0}], "raw_calls": [{"caller_nid": "layout_navbar_isactive", "callee": "startsWith", "is_member_call": true, "source_file": "C:\\Users\\jaisi\\Documents\\React Projects\\gts-katha\\components\\layout\\Navbar.tsx", "source_location": "L52"}, {"caller_nid": "layout_navbar_handlelogout", "callee": "setMobileOpen", "is_member_call": false, "source_file": "C:\\Users\\jaisi\\Documents\\React Projects\\gts-katha\\components\\layout\\Navbar.tsx", "source_location": "L56"}, {"caller_nid": "layout_navbar_handlelogout", "callee": "signOut", "is_member_call": false, "source_file": "C:\\Users\\jaisi\\Documents\\React Projects\\gts-katha\\components\\layout\\Navbar.tsx", "source_location": "L57"}, {"caller_nid": "layout_navbar_handlelogout", "callee": "success", "is_member_call": true, "source_file": "C:\\Users\\jaisi\\Documents\\React Projects\\gts-katha\\components\\layout\\Navbar.tsx", "source_location": "L58"}, {"caller_nid": "layout_navbar_handlelogout", "callee": "assign", "is_member_call": true, "source_file": "C:\\Users\\jaisi\\Documents\\React Projects\\gts-katha\\components\\layout\\Navbar.tsx", "source_location": "L59"}]}